commoneval/__init__.py
commoneval/dataset.py
commoneval/item.py
commoneval/makeitems.py
commoneval/util/__init__.py
commoneval/util/f1.py
commoneval/util/gleu.py
commoneval-0.2.1.dist-info/METADATA
commoneval-0.2.1.dist-info/WHEEL
commoneval-0.2.1.dist-info/licenses/LICENSE
commoneval-0.2.1.dist-info/RECORD
